{"ladder_id":"6","ladder_name":"Codeforces Div. 2, C","ladders":[{"id":"1","name":"Given Length and Sum of Digits...","link":"http://codeforces.com/problemset/problem/489/C","difficulty_level":"1"},{"id":"2","name":"Number of Ways","link":"http://codeforces.com/problemset/problem/466/C","difficulty_level":"4"},{"id":"3","name":"Team","link":"http://codeforces.com/problemset/problem/401/C","difficulty_level":"4"},{"id":"4","name":"Exams","link":"http://codeforces.com/problemset/problem/479/C","difficulty_level":"4"},{"id":"5","name":"Boredom","link":"http://codeforces.com/problemset/problem/455/A","difficulty_level":"4"},{"id":"6","name":"Table Decorations","link":"http://codeforces.com/problemset/problem/478/C","difficulty_level":"4"},{"id":"7","name":"Beautiful Sets of Points","link":"http://codeforces.com/problemset/problem/268/C","difficulty_level":"4"},{"id":"8","name":"k-Tree","link":"http://codeforces.com/problemset/problem/431/C","difficulty_level":"4"},{"id":"9","name":"Valera and Tubes ","link":"http://codeforces.com/problemset/problem/441/C","difficulty_level":"4"},{"id":"10","name":"Palindrome Transformation","link":"http://codeforces.com/problemset/problem/486/C","difficulty_level":"4"},{"id":"11","name":"Fixing Typos","link":"http://codeforces.com/problemset/problem/363/C","difficulty_level":"4"},{"id":"12","name":"Hacking Cypher","link":"http://codeforces.com/problemset/problem/490/C","difficulty_level":"2"},{"id":"13","name":"Gargari and Bishops","link":"http://codeforces.com/problemset/problem/463/C","difficulty_level":"5"},{"id":"14","name":"Pocket Book","link":"http://codeforces.com/problemset/problem/152/C","difficulty_level":"4"},{"id":"15","name":"Lucky Sum of Digits","link":"http://codeforces.com/problemset/problem/109/A","difficulty_level":"3"},{"id":"16","name":"Arithmetic Progression","link":"http://codeforces.com/problemset/problem/382/C","difficulty_level":"4"},{"id":"17","name":"Fox and Box Accumulation","link":"http://codeforces.com/problemset/problem/388/A","difficulty_level":"3"},{"id":"18","name":"Hexadecimal's Numbers","link":"http://codeforces.com/problemset/problem/9/C","difficulty_level":"2"},{"id":"19","name":"Xenia and Weights","link":"http://codeforces.com/problemset/problem/339/C","difficulty_level":"4"},{"id":"20","name":"Bombs","link":"http://codeforces.com/problemset/problem/350/C","difficulty_level":"4"},{"id":"21","name":"Pashmak and Buses","link":"http://codeforces.com/problemset/problem/459/C","difficulty_level":"5"},{"id":"22","name":"Little Elephant and Problem","link":"http://codeforces.com/problemset/problem/220/A","difficulty_level":"4"},{"id":"23","name":"Maze","link":"http://codeforces.com/problemset/problem/377/A","difficulty_level":"4"},{"id":"24","name":"Ice Skating","link":"http://codeforces.com/problemset/problem/217/A","difficulty_level":"3"},{"id":"25","name":"Hamburgers","link":"http://codeforces.com/problemset/problem/371/C","difficulty_level":"4"},{"id":"26","name":"Bear and Prime Numbers","link":"http://codeforces.com/problemset/problem/385/C","difficulty_level":"5"},{"id":"27","name":"History","link":"http://codeforces.com/problemset/problem/137/C","difficulty_level":"4"},{"id":"28","name":"Checkposts","link":"http://codeforces.com/problemset/problem/427/C","difficulty_level":"4"},{"id":"29","name":"Mashmokh and Numbers","link":"http://codeforces.com/problemset/problem/414/A","difficulty_level":"3"},{"id":"30","name":"Ladder","link":"http://codeforces.com/problemset/problem/279/C","difficulty_level":"4"},{"id":"31","name":"Escape from Stones","link":"http://codeforces.com/problemset/problem/264/A","difficulty_level":"3"},{"id":"32","name":"Division into Teams","link":"http://codeforces.com/problemset/problem/149/C","difficulty_level":"4"},{"id":"33","name":"Barcode","link":"http://codeforces.com/problemset/problem/225/C","difficulty_level":"4"},{"id":"34","name":"Stripe","link":"http://codeforces.com/problemset/problem/18/C","difficulty_level":"3"},{"id":"35","name":"Mafia","link":"http://codeforces.com/problemset/problem/348/A","difficulty_level":"4"},{"id":"36","name":"Cows and Sequence","link":"http://codeforces.com/problemset/problem/283/A","difficulty_level":"4"},{"id":"37","name":"To Add or Not to Add","link":"http://codeforces.com/problemset/problem/231/C","difficulty_level":"4"},{"id":"38","name":"Xor-tree","link":"http://codeforces.com/problemset/problem/429/A","difficulty_level":"3"},{"id":"39","name":"LCM Challenge","link":"http://codeforces.com/problemset/problem/235/A","difficulty_level":"4"},{"id":"40","name":"Rational Resistance","link":"http://codeforces.com/problemset/problem/343/A","difficulty_level":"4"},{"id":"41","name":"Points on Line","link":"http://codeforces.com/problemset/problem/251/A","difficulty_level":"3"},{"id":"42","name":"No to Palindromes!","link":"http://codeforces.com/problemset/problem/464/A","difficulty_level":"4"},{"id":"43","name":"Magic Formulas","link":"http://codeforces.com/problemset/problem/424/C","difficulty_level":"4"},{"id":"44","name":"Beautiful Numbers","link":"http://codeforces.com/problemset/problem/300/C","difficulty_level":"4"},{"id":"45","name":"Quiz","link":"http://codeforces.com/problemset/problem/337/C","difficulty_level":"4"},{"id":"46","name":"Replacement","link":"http://codeforces.com/problemset/problem/135/A","difficulty_level":"3"},{"id":"47","name":"Vasya and Robot","link":"http://codeforces.com/problemset/problem/354/A","difficulty_level":"4"},{"id":"48","name":"Captain Marmot","link":"http://codeforces.com/problemset/problem/474/C","difficulty_level":"4"},{"id":"49","name":"Win or Freeze","link":"http://codeforces.com/problemset/problem/150/A","difficulty_level":"4"},{"id":"50","name":"Matrix","link":"http://codeforces.com/problemset/problem/364/A","difficulty_level":"4"},{"id":"51","name":"Little Frog","link":"http://codeforces.com/problemset/problem/53/C","difficulty_level":"2"},{"id":"52","name":"Lucky Sum","link":"http://codeforces.com/problemset/problem/121/A","difficulty_level":"3"},{"id":"53","name":"Fight the Monster","link":"http://codeforces.com/problemset/problem/487/A","difficulty_level":"4"},{"id":"54","name":"Triangle","link":"http://codeforces.com/problemset/problem/407/A","difficulty_level":"4"},{"id":"55","name":"View Angle","link":"http://codeforces.com/problemset/problem/257/C","difficulty_level":"4"},{"id":"56","name":"King's Path","link":"http://codeforces.com/problemset/problem/242/C","difficulty_level":"4"},{"id":"57","name":"Round Table Knights","link":"http://codeforces.com/problemset/problem/71/C","difficulty_level":"4"},{"id":"58","name":"Purification","link":"http://codeforces.com/problemset/problem/329/A","difficulty_level":"4"},{"id":"59","name":"Maxim and Discounts","link":"http://codeforces.com/problemset/problem/261/A","difficulty_level":"3"},{"id":"60","name":"The Closest Pair","link":"http://codeforces.com/problemset/problem/311/A","difficulty_level":"3"},{"id":"61","name":"Divisible by Seven","link":"http://codeforces.com/problemset/problem/375/A","difficulty_level":"4"},{"id":"62","name":"Hometask","link":"http://codeforces.com/problemset/problem/154/A","difficulty_level":"4"},{"id":"63","name":"Little Elephant and Interval","link":"http://codeforces.com/problemset/problem/204/A","difficulty_level":"4"},{"id":"64","name":"Dorm Water Supply","link":"http://codeforces.com/problemset/problem/107/A","difficulty_level":"3"},{"id":"65","name":"Shaass and Lights","link":"http://codeforces.com/problemset/problem/294/C","difficulty_level":"5"},{"id":"66","name":"Prime Number","link":"http://codeforces.com/problemset/problem/359/C","difficulty_level":"5"},{"id":"67","name":"The Brand New Function","link":"http://codeforces.com/problemset/problem/243/A","difficulty_level":"4"},{"id":"68","name":"About Bacteria","link":"http://codeforces.com/problemset/problem/198/A","difficulty_level":"4"},{"id":"69","name":"Malek Dance Club","link":"http://codeforces.com/problemset/problem/319/A","difficulty_level":"4"},{"id":"70","name":"Dima and Containers","link":"http://codeforces.com/problemset/problem/358/C","difficulty_level":"5"},{"id":"71","name":"Trains","link":"http://codeforces.com/problemset/problem/87/A","difficulty_level":"4"},{"id":"72","name":"Almost Arithmetical Progression","link":"http://codeforces.com/problemset/problem/255/C","difficulty_level":"4"},{"id":"73","name":"Newspaper Headline","link":"http://codeforces.com/problemset/problem/91/A","difficulty_level":"4"},{"id":"74","name":"Inna and Dima","link":"http://codeforces.com/problemset/problem/374/C","difficulty_level":"4"},{"id":"75","name":"Hiring Staff","link":"http://codeforces.com/problemset/problem/216/C","difficulty_level":"5"},{"id":"76","name":"STL","link":"http://codeforces.com/problemset/problem/190/C","difficulty_level":"4"},{"id":"77","name":"Prime Permutation","link":"http://codeforces.com/problemset/problem/123/A","difficulty_level":"4"},{"id":"78","name":"Four Segments","link":"http://codeforces.com/problemset/problem/14/C","difficulty_level":"5"},{"id":"79","name":"Fire Again","link":"http://codeforces.com/problemset/problem/35/C","difficulty_level":"4"},{"id":"80","name":"Below the Diagonal","link":"http://codeforces.com/problemset/problem/266/C","difficulty_level":"6"},{"id":"81","name":"Mail Stamps","link":"http://codeforces.com/problemset/problem/29/C","difficulty_level":"4"},{"id":"82","name":"Grammar Lessons","link":"http://codeforces.com/problemset/problem/113/A","difficulty_level":"4"},{"id":"83","name":"Bracket Sequence","link":"http://codeforces.com/problemset/problem/223/A","difficulty_level":"4"},{"id":"84","name":"Heroes","link":"http://codeforces.com/problemset/problem/77/A","difficulty_level":"4"},{"id":"85","name":"Literature Lesson","link":"http://codeforces.com/problemset/problem/138/A","difficulty_level":"4"},{"id":"86","name":"Reducing Fractions","link":"http://codeforces.com/problemset/problem/222/C","difficulty_level":"5"},{"id":"87","name":"Game","link":"http://codeforces.com/problemset/problem/213/A","difficulty_level":"4"},{"id":"88","name":"Cutting Figure","link":"http://codeforces.com/problemset/problem/193/A","difficulty_level":"4"},{"id":"89","name":"Trees","link":"http://codeforces.com/problemset/problem/58/C","difficulty_level":"4"},{"id":"90","name":"Hockey","link":"http://codeforces.com/problemset/problem/95/A","difficulty_level":"4"},{"id":"91","name":"Schedule","link":"http://codeforces.com/problemset/problem/31/C","difficulty_level":"4"},{"id":"92","name":"Rectangle Puzzle","link":"http://codeforces.com/problemset/problem/280/A","difficulty_level":"5"},{"id":"93","name":"Disposition","link":"http://codeforces.com/problemset/problem/49/C","difficulty_level":"4"},{"id":"94","name":"Flea","link":"http://codeforces.com/problemset/problem/32/C","difficulty_level":"4"},{"id":"95","name":"Help Victoria the Wise","link":"http://codeforces.com/problemset/problem/98/A","difficulty_level":"4"},{"id":"96","name":"Corporation Mail","link":"http://codeforces.com/problemset/problem/56/C","difficulty_level":"4"},{"id":"97","name":"Optimal Sum","link":"http://codeforces.com/problemset/problem/182/C","difficulty_level":"5"},{"id":"98","name":"On Number of Decompositions into Multipliers","link":"http://codeforces.com/problemset/problem/396/A","difficulty_level":"7"},{"id":"99","name":"Blocked Points","link":"http://codeforces.com/problemset/problem/392/A","difficulty_level":"7"},{"id":"100","name":"Crossword","link":"http://codeforces.com/problemset/problem/47/C","difficulty_level":"5"}]}